augint_library/__init__.py
augint_library/cli.py
augint_library/constants.py
augint_library/core.py
augint_library/exceptions.py
augint_library/feature_flags.py
augint_library/logging.py
augint_library/protocols.py
augint_library/py.typed
augint_library/resilience.py
augint_library/telemetry.py
augint_library-1.31.0.dist-info/LICENSE
augint_library-1.31.0.dist-info/METADATA
augint_library-1.31.0.dist-info/WHEEL
augint_library-1.31.0.dist-info/entry_points.txt
augint_library-1.31.0.dist-info/RECORD
