Metadata-Version: 2.3
Name: augint-library
Version: 1.31.0
Summary: A template library for Python library projects using Poetry and Semantic Release.
License: Copyright (c) Augmenting Integrations LLC
Author: Samuel Vange
Author-email: 7166607+svange@users.noreply.github.com
Requires-Python: >=3.9,<4.0
Classifier: License :: Other/Proprietary License
Classifier: Programming Language :: Python :: 3
Classifier: Programming Language :: Python :: 3.9
Classifier: Programming Language :: Python :: 3.10
Classifier: Programming Language :: Python :: 3.11
Classifier: Programming Language :: Python :: 3.12
Classifier: Programming Language :: Python :: 3.13
Requires-Dist: click (>=8.1.0,<8.2.0)
Requires-Dist: toml (>=0.10.0,<1.0.0)
